Metadata-Version: 2.2
Name: botenv
Version: 0.1.0
Summary: Class to set and load environment variables
Home-page: https://github.com/botlorien/botenv
Author: Ben-Hur P. B. Santos
Author-email: botlorien@gmail.com
Classifier: Programming Language :: Python :: 3
Classifier: License :: OSI Approved :: MIT License
Classifier: Operating System :: OS Independent
Requires-Python: >=3.10
License-File: LICENSE
Dynamic: author
Dynamic: author-email
Dynamic: classifier
Dynamic: description
Dynamic: description-content-type
Dynamic: home-page
Dynamic: requires-python
Dynamic: summary
